auto_favicon/__init__.py
auto_favicon/__main__.py
auto_favicon/server.py
iflow_mcp_auto_favicon-1.0.1.dist-info/METADATA
iflow_mcp_auto_favicon-1.0.1.dist-info/WHEEL
iflow_mcp_auto_favicon-1.0.1.dist-info/entry_points.txt
iflow_mcp_auto_favicon-1.0.1.dist-info/licenses/LICENSE
iflow_mcp_auto_favicon-1.0.1.dist-info/RECORD
