Metadata-Version: 2.4
Name: iflow-mcp_auto-favicon
Version: 1.0.1
Summary: A Model Context Protocol server providing tools for automatic favicon generation from PNG images or URLs
Author-email: Lee <hua337@icloud.com>
License: MIT
License-File: LICENSE
Keywords: favicon,image-processing,llm,mcp,web-development
Classifier: Intended Audience :: Developers
Classifier: License :: OSI Approved :: MIT License
Classifier: Programming Language :: Python :: 3
Classifier: Programming Language :: Python :: 3.12
Classifier: Topic :: Internet :: WWW/HTTP :: Dynamic Content
Classifier: Topic :: Multimedia :: Graphics :: Graphics Conversion
Classifier: Topic :: Software Development :: Libraries :: Python Modules
Requires-Python: >=3.12
Requires-Dist: aiohttp>=3.9.0
Requires-Dist: mcp>=1.12.0
Requires-Dist: pathlib2>=2.3.7
Requires-Dist: pillow>=10.0.0
Requires-Dist: requests>=2.31.0
